omniconf/__init__.py
omniconf/config.py
omniconf/exceptions.py
omniconf/keys.py
omniconf/loader.py
omniconf/py.typed
omniconf/setting.py
omniconf/types.py
omniconf/usage.py
omniconf/backends/__init__.py
omniconf/backends/argparse.py
omniconf/backends/configobj.py
omniconf/backends/env.py
omniconf/backends/generic.py
omniconf/backends/json.py
omniconf/backends/toml.py
omniconf/backends/yaml.py
omniconf/mypy/__init__.py
omniconf/mypy/plugin.py
omniconf/tests/__init__.py
omniconf/tests/test_config.py
omniconf/tests/test_keys.py
omniconf/tests/test_loader.py
omniconf/tests/test_setting.py
omniconf/tests/test_types.py
omniconf/tests/test_usage.py
omniconf/tests/backends/__init__.py
omniconf/tests/backends/test_argparse.py
omniconf/tests/backends/test_argparse_usage.py
omniconf/tests/backends/test_configobj.py
omniconf/tests/backends/test_env.py
omniconf/tests/backends/test_generic.py
omniconf/tests/backends/test_json.py
omniconf/tests/backends/test_toml.py
omniconf/tests/backends/test_yaml.py
omniconf-1.5.1.dist-info/AUTHORS
omniconf-1.5.1.dist-info/LICENSE
omniconf-1.5.1.dist-info/METADATA
omniconf-1.5.1.dist-info/WHEEL
omniconf-1.5.1.dist-info/pbr.json
omniconf-1.5.1.dist-info/top_level.txt
omniconf-1.5.1.dist-info/RECORD
