Metadata-Version: 2.1
Name: omniconf
Version: 1.5.1
Summary: A Python library that makes configuring your application independent from your configuration backend.
Home-page: https://gitlab.com/CYSO/open-source/omniconf
Author: Nick Douma
Author-email: n.douma@nekoconeko.nl
License: LGPLv3
Keywords: omniconf,config,configuration
Classifier: Development Status :: 5 - Production/Stable
Classifier: Intended Audience :: Developers
Classifier: Intended Audience :: Information Technology
Classifier: Intended Audience :: System Administrators
Classifier: License :: OSI Approved :: GNU Lesser General Public License v3 or later (LGPLv3+)
Classifier: Operating System :: POSIX
Classifier: Operating System :: POSIX :: Linux
Classifier: Operating System :: Unix
Classifier: Programming Language :: Python :: 3
Classifier: Programming Language :: Python :: 3.8
Classifier: Programming Language :: Python :: 3.9
Classifier: Programming Language :: Python :: 3.10
Classifier: Programming Language :: Python :: 3.11
Classifier: Programming Language :: Python :: 3.12
Classifier: Programming Language :: Python :: Implementation :: CPython
Classifier: Programming Language :: Python :: Implementation :: PyPy
Classifier: Topic :: Software Development :: Libraries :: Python Modules
Classifier: Topic :: Software Development :: User Interfaces
Classifier: Topic :: System :: Installation/Setup
Classifier: Topic :: Utilities
License-File: LICENSE
License-File: AUTHORS
Provides-Extra: configobj
Requires-Dist: configobj ; extra == 'configobj'
Provides-Extra: toml
Requires-Dist: toml ; extra == 'toml'
Provides-Extra: yaml
Requires-Dist: PyYAML ; extra == 'yaml'
